mlpLogger/__init__.py
mlpLogger/mlpLogger.py
mlplogger-0.1.0.dist-info/licenses/LICENSE
mlplogger-0.1.0.dist-info/METADATA
mlplogger-0.1.0.dist-info/WHEEL
mlplogger-0.1.0.dist-info/top_level.txt
mlplogger-0.1.0.dist-info/RECORD
