Metadata-Version: 2.4
Name: mlpLogger
Version: 0.1.0
Summary: A Python package to set up structured logging for your applications.
Home-page: https://github.com/yourusername/mlpLogger
Author: Michael Baskaran
Author-email: Michael Baskaran <mbas@caasco.ca>
Requires-Python: >=3.7
License-File: LICENSE
Requires-Dist: ecs-logging
Dynamic: author
Dynamic: home-page
Dynamic: license-file
Dynamic: requires-python
